django_feedparser/__init__.py
django_feedparser/models.py
django_feedparser/renderer.py
django_feedparser/settings.py
django_feedparser/templates/django_feedparser/basic_feed_renderer.html
django_feedparser/templates/django_feedparser/view.html
django_feedparser/templatetags/__init__.py
django_feedparser/templatetags/feedparser_tags.py
django_feedparser/urls.py
django_feedparser/utils.py
django_feedparser/views.py
django3_feedparser-2.0.1.dist-info/WHEEL
django3_feedparser-2.0.1.dist-info/METADATA
django3_feedparser-2.0.1.dist-info/RECORD
