Metadata-Version: 2.1
Name: django3-feedparser
Version: 2.0.1
Summary: A Django app using feedparser to fetch and parse a feed to render it from a template.
Home-page: https://github.com/ImaginaryLandscape/django3-feedparser
License: MIT
Author: David Thenon
Author-email: dthenon@emencia.com
Maintainer: Imagescape
Maintainer-email: info@imagescape.com
Requires-Python: >=3.7,<4.0
Classifier: License :: OSI Approved :: MIT License
Classifier: Programming Language :: Python :: 3
Classifier: Programming Language :: Python :: 3.10
Classifier: Programming Language :: Python :: 3.7
Classifier: Programming Language :: Python :: 3.8
Classifier: Programming Language :: Python :: 3.9
Requires-Dist: feedparser (>=6.0.10,<7.0.0)
Requires-Dist: requests (>=2.28.0,<3.0.0)
Requires-Dist: six (>=1.16.0,<2.0.0)
